xslha/__init__.py
xslha/main.py
xslha/xslha.py
xslha-1.0.3.dist-info/LICENSE
xslha-1.0.3.dist-info/METADATA
xslha-1.0.3.dist-info/WHEEL
xslha-1.0.3.dist-info/top_level.txt
xslha-1.0.3.dist-info/RECORD
