Metadata-Version: 2.1
Name: xslha
Version: 1.0.3
Summary: A python package to read (big/many) SLHA files
Home-page: https://github.com/fstaub/xSLHA
Author: Florian Staub
Author-email: florian.staub@gmail.com
License: UNKNOWN
Platform: UNKNOWN
Classifier: Programming Language :: Python :: 3
Classifier: Programming Language :: Python :: 2
Classifier: License :: OSI Approved :: MIT License
Classifier: Operating System :: POSIX :: Linux
Classifier: Operating System :: MacOS
